README.md
setup.py
tenable_ibm_cp4s/__init__.py
tenable_ibm_cp4s/cli.py
tenable_ibm_cp4s/transform.py
tenable_ibm_cp4s.egg-info/PKG-INFO
tenable_ibm_cp4s.egg-info/SOURCES.txt
tenable_ibm_cp4s.egg-info/dependency_links.txt
tenable_ibm_cp4s.egg-info/entry_points.txt
tenable_ibm_cp4s.egg-info/requires.txt
tenable_ibm_cp4s.egg-info/top_level.txt
tenable_ibm_cp4s/cloudpak4sec/__init__.py
tenable_ibm_cp4s/cloudpak4sec/collections.py
tenable_ibm_cp4s/cloudpak4sec/databases.py
tenable_ibm_cp4s/cloudpak4sec/ingest.py
tenable_ibm_cp4s/cloudpak4sec/jobs.py